CHANGELOG.txt
CODE_OF_CONDUCT.md
CONTRIBUTORS.rst
LICENSE
MANIFEST.in
README.md
SECURITY.md
SPONSORS.md
setup.cfg
setup.py
sifter_wagtail.egg-info/PKG-INFO
sifter_wagtail.egg-info/SOURCES.txt
sifter_wagtail.egg-info/dependency_links.txt
sifter_wagtail.egg-info/entry_points.txt
sifter_wagtail.egg-info/not-zip-safe
sifter_wagtail.egg-info/requires.txt
sifter_wagtail.egg-info/top_level.txt
wagtail/__init__.py
wagtail/admin/.gitignore
wagtail/admin/__init__.py
wagtail/admin/action_menu.py
wagtail/admin/apps.py
wagtail/admin/auth.py
wagtail/admin/blocks.py
wagtail/admin/checks.py
wagtail/admin/compare.py
wagtail/admin/datetimepicker.py
wagtail/admin/edit_handlers.py
wagtail/admin/filters.py
wagtail/admin/jinja2tags.py
wagtail/admin/localization.py
wagtail/admin/log_action_registry.py
wagtail/admin/mail.py
wagtail/admin/menu.py
wagtail/admin/messages.py
wagtail/admin/modal_workflow.py
wagtail/admin/models.py
wagtail/admin/navigation.py
wagtail/admin/search.py
wagtail/admin/signal_handlers.py
wagtail/admin/signals.py
wagtail/admin/site_summary.py
wagtail/admin/staticfiles.py
wagtail/admin/userbar.py
wagtail/admin/wagtail_hooks.py
wagtail/admin/api/__init__.py
wagtail/admin/api/filters.py
wagtail/admin/api/serializers.py
wagtail/admin/api/urls.py
wagtail/admin/api/views.py
wagtail/admin/forms/__init__.py
wagtail/admin/forms/auth.py
wagtail/admin/forms/choosers.py
wagtail/admin/forms/collections.py
wagtail/admin/forms/models.py
wagtail/admin/forms/pages.py
wagtail/admin/forms/search.py
wagtail/admin/forms/tags.py
wagtail/admin/forms/view_restrictions.py
wagtail/admin/forms/workflows.py
wagtail/admin/locale/af/LC_MESSAGES/django.mo
wagtail/admin/locale/ar/LC_MESSAGES/django.mo
wagtail/admin/locale/ar/LC_MESSAGES/django.po
wagtail/admin/locale/az_AZ/LC_MESSAGES/django.mo
wagtail/admin/locale/az_AZ/LC_MESSAGES/django.po
wagtail/admin/locale/be/LC_MESSAGES/django.mo
wagtail/admin/locale/be/LC_MESSAGES/django.po
wagtail/admin/locale/bg/LC_MESSAGES/django.mo
wagtail/admin/locale/bg/LC_MESSAGES/django.po
wagtail/admin/locale/bn/LC_MESSAGES/django.mo
wagtail/admin/locale/bn/LC_MESSAGES/django.po
wagtail/admin/locale/ca/LC_MESSAGES/django.mo
wagtail/admin/locale/ca/LC_MESSAGES/django.po
wagtail/admin/locale/cs/LC_MESSAGES/django.mo
